README.rst
setup.cfg
setup.py
fnv/__init__.py
fnv.egg-info/PKG-INFO
fnv.egg-info/SOURCES.txt
fnv.egg-info/dependency_links.txt
fnv.egg-info/not-zip-safe
fnv.egg-info/top_level.txt