Metadata-Version: 1.0
Name: fnv
Version: 0.1.0
Summary: FNV hash functions.
Home-page: https://github.com/povilasb/pyfnv
Author: Povilas Balciunas
Author-email: balciunas90@gmail.com
License: MIT
Platform: UNKNOWN
